dragonfly/_tracing.py
dragonfly/_interface.py
dragonfly/_maxilla.pyi
dragonfly/_transformation.py
dragonfly/_version.py
dragonfly/_module.py
dragonfly/bite.py
dragonfly/_injection.py
dragonfly/__init__.py
dragonfly/_settings.py
dragonfly/_notify.py
dragonfly/_maxilla.c
dragonfly/__about__.py
dragonfly/_debugger.py
dragonfly/_maxilla.cpython-311-darwin.so
dragonfly/_commands.py
dragonfly/__main__.py
dragonfly/_breakpoint/registry.py
dragonfly/_breakpoint/__init__.py
dragonfly/_breakpoint/model.py
dragonfly/_bootstrap/preload.py
dragonfly/_bootstrap/sitecustomize.py
dfly-0.2.1.dist-info/RECORD
dfly-0.2.1.dist-info/WHEEL
dfly-0.2.1.dist-info/entry_points.txt
dfly-0.2.1.dist-info/top_level.txt
dfly-0.2.1.dist-info/LICENSE.txt
dfly-0.2.1.dist-info/METADATA
