Metadata-Version: 2.1
Name: dfly
Version: 0.2.1
Summary: Lightweight CPython Debugger
Author: Gabriele N. Tornetta
Author-email: "Gabriele N. Tornetta" <phoenix1987@gmail.com>
Project-URL: Documentation, https://github.com/P403n1x87/dragonfly#readme
Project-URL: Issues, https://github.com/P403n1x87/dragonfly/issues
Project-URL: Source, https://github.com/P403n1x87/dragonfly
Classifier: Development Status :: 4 - Beta
Classifier: Programming Language :: Python
Classifier: Programming Language :: Python :: 3.8
Classifier: Programming Language :: Python :: 3.9
Classifier: Programming Language :: Python :: 3.10
Classifier: Programming Language :: Python :: 3.11
Classifier: Programming Language :: Python :: 3.12
Classifier: Programming Language :: Python :: Implementation :: CPython
Classifier: Programming Language :: Python :: Implementation :: PyPy
Requires-Python: >=3.8
License-File: LICENSE.txt
Requires-Dist: spasmlang~=0.2.0
